<?xml version="1.0" encoding="UTF-8" standalone="no"?>
<databaseChangeLog xmlns="http://www.liquibase.org/xml/ns/dbchangelog" xmlns:ext="http://www.liquibase.org/xml/ns/dbchangelog-ext" xmlns:xsi="http://www.w3.org/2001/XMLSchema-instance" xsi:schemaLocation="http://www.liquibase.org/xml/ns/dbchangelog-ext http://www.liquibase.org/xml/ns/dbchangelog/dbchangelog-ext.xsd http://www.liquibase.org/xml/ns/dbchangelog http://www.liquibase.org/xml/ns/dbchangelog/dbchangelog-3.4.xsd">
    <changeSet author="oyas (generated)" id="1467650592995-1">
        <createTable tableName="TCC_CONTACT_REL_DEF">
            <column autoIncrement="true" name="ID" type="BIGINT">
                <constraints primaryKey="true" primaryKeyName="TCC_CONTACT_REL_DEFPK"/>
            </column>
            <column name="ISACTIVE" type="BOOLEAN"/>
            <column name="CODE" type="VARCHAR(30)">
                <constraints nullable="false"/>
            </column>
            <column name="INFO" type="VARCHAR(255)"/>
            <column name="NAME" type="VARCHAR(100)">
                <constraints nullable="false"/>
            </column>
            <column name="ROLES" type="VARCHAR(255)"/>
        </createTable>
    </changeSet>
    <changeSet author="oyas (generated)" id="1467650592995-2">
        <addForeignKeyConstraint baseColumnNames="LOCATION_ID" baseTableName="TCC_CONTACT_INFO" constraintName="FK_CONADDR_LOC" deferrable="false" initiallyDeferred="false" referencedColumnNames="ID" referencedTableName="TCO_LOCATION"/>
    </changeSet>
    <changeSet author="oyas (generated)" id="1467650592995-3">
        <addForeignKeyConstraint baseColumnNames="COMMODITY_ID" baseTableName="TCC_CONTACT_COMMODITY" constraintName="FK_CONCOMM_COMMODITY" deferrable="false" initiallyDeferred="false" referencedColumnNames="ID" referencedTableName="TCO_COMMOTITY"/>
    </changeSet>
    <changeSet author="oyas (generated)" id="1467650592995-4">
        <addForeignKeyConstraint baseColumnNames="CONTACT_ID" baseTableName="TCC_CONTACT_COMMODITY" constraintName="FK_CONCOMM_CONTACT" deferrable="false" initiallyDeferred="false" referencedColumnNames="ID" referencedTableName="TCC_CONTACT"/>
    </changeSet>
    <changeSet author="oyas (generated)" id="1467650592995-5">
        <addForeignKeyConstraint baseColumnNames="CONTACT_ID" baseTableName="TCC_CONTACT_INFO" constraintName="FK_CONINF_CONTACT" deferrable="false" initiallyDeferred="false" referencedColumnNames="ID" referencedTableName="TCC_CONTACT"/>
    </changeSet>
    <changeSet author="oyas (generated)" id="1467650592995-6">
        <addForeignKeyConstraint baseColumnNames="RELEATION_ID" baseTableName="TCC_CONTACT_REL" constraintName="FK_CONREL_REL" deferrable="false" initiallyDeferred="false" referencedColumnNames="ID" referencedTableName="TCC_CONTACT_REL_DEF"/>
    </changeSet>
    <changeSet author="oyas (generated)" id="1467650592995-7">
        <addForeignKeyConstraint baseColumnNames="SOURCE_ID" baseTableName="TCC_CONTACT_REL" constraintName="FK_CONREL_SOURCE" deferrable="false" initiallyDeferred="false" referencedColumnNames="ID" referencedTableName="TCC_CONTACT"/>
    </changeSet>
    <changeSet author="oyas (generated)" id="1467650592995-8">
        <addForeignKeyConstraint baseColumnNames="TARGET_ID" baseTableName="TCC_CONTACT_REL" constraintName="FK_CONREL_TARGET" deferrable="false" initiallyDeferred="false" referencedColumnNames="ID" referencedTableName="TCC_CONTACT"/>
    </changeSet>
    <changeSet author="oyas (generated)" id="1467650592995-9">
        <addForeignKeyConstraint baseColumnNames="ADDR_ID" baseTableName="TCC_CONTACT" constraintName="FK_CON_ADDR" deferrable="false" initiallyDeferred="false" referencedColumnNames="ID" referencedTableName="TCC_CONTACT_INFO"/>
    </changeSet>
    <changeSet author="oyas (generated)" id="1467650592995-10">
        <addForeignKeyConstraint baseColumnNames="CAT_ID" baseTableName="TCC_CONTACT" constraintName="FK_CON_CAT" deferrable="false" initiallyDeferred="false" referencedColumnNames="ID" referencedTableName="TCC_CONTACT_CAT"/>
    </changeSet>
    <changeSet author="oyas (generated)" id="1467650592995-11">
        <addForeignKeyConstraint baseColumnNames="EMAIL_ID" baseTableName="TCC_CONTACT" constraintName="FK_CON_EMAIL" deferrable="false" initiallyDeferred="false" referencedColumnNames="ID" referencedTableName="TCC_CONTACT_INFO"/>
    </changeSet>
    <changeSet author="oyas (generated)" id="1467650592995-12">
        <addForeignKeyConstraint baseColumnNames="FAX_ID" baseTableName="TCC_CONTACT" constraintName="FK_CON_FAX" deferrable="false" initiallyDeferred="false" referencedColumnNames="ID" referencedTableName="TCC_CONTACT_INFO"/>
    </changeSet>
    <changeSet author="oyas (generated)" id="1467650592995-13">
        <addForeignKeyConstraint baseColumnNames="INDUSTRY_ID" baseTableName="TCC_CONTACT" constraintName="FK_CON_INDUSTRY" deferrable="false" initiallyDeferred="false" referencedColumnNames="ID" referencedTableName="TCO_INDUSTRY"/>
    </changeSet>
    <changeSet author="oyas (generated)" id="1467650592995-14">
        <addForeignKeyConstraint baseColumnNames="MOBILE_ID" baseTableName="TCC_CONTACT" constraintName="FK_CON_MOBILE" deferrable="false" initiallyDeferred="false" referencedColumnNames="ID" referencedTableName="TCC_CONTACT_INFO"/>
    </changeSet>
    <changeSet author="oyas (generated)" id="1467650592995-15">
        <addForeignKeyConstraint baseColumnNames="PHONE_ID" baseTableName="TCC_CONTACT" constraintName="FK_CON_PHONE" deferrable="false" initiallyDeferred="false" referencedColumnNames="ID" referencedTableName="TCC_CONTACT_INFO"/>
    </changeSet>
    <changeSet author="oyas (generated)" id="1467650592995-16">
        <addForeignKeyConstraint baseColumnNames="TERRITORY_ID" baseTableName="TCC_CONTACT" constraintName="FK_CON_TER" deferrable="false" initiallyDeferred="false" referencedColumnNames="ID" referencedTableName="TCO_TERRITORY"/>
    </changeSet>
    <changeSet author="oyas (generated)" id="1467650592995-17">
        <addForeignKeyConstraint baseColumnNames="PARENT_ID" baseTableName="TCC_CONTACT" constraintName="FK_CORP_PARENT" deferrable="false" initiallyDeferred="false" referencedColumnNames="ID" referencedTableName="TCC_CONTACT"/>
    </changeSet>
    <changeSet author="oyas (generated)" id="1467650592995-18">
        <addForeignKeyConstraint baseColumnNames="CONTACT_ID" baseTableName="TCC_CONTACT" constraintName="FK_CORP_PER" deferrable="false" initiallyDeferred="false" referencedColumnNames="ID" referencedTableName="TCC_CONTACT"/>
    </changeSet>
    <changeSet author="oyas (generated)" id="1467650592995-19">
        <addForeignKeyConstraint baseColumnNames="TYPE_ID" baseTableName="TCC_CONTACT" constraintName="FK_CORP_TYPE" deferrable="false" initiallyDeferred="false" referencedColumnNames="ID" referencedTableName="TCC_CORP_TYPE"/>
    </changeSet>
    <changeSet author="oyas (generated)" id="1467650592995-20">
        <addForeignKeyConstraint baseColumnNames="CORP_ID" baseTableName="TCC_CONTACT" constraintName="FK_PER_CORP" deferrable="false" initiallyDeferred="false" referencedColumnNames="ID" referencedTableName="TCC_CONTACT"/>
    </changeSet>
    <changeSet author="oyas (generated)" id="1467650592995-21">
        <addForeignKeyConstraint baseColumnNames="PID" baseTableName="TCC_CONTACT_CAT" constraintName="FK_sjkf2ep6fcrq182sdjar52ttb" deferrable="false" initiallyDeferred="false" referencedColumnNames="ID" referencedTableName="TCC_CONTACT_CAT"/>
    </changeSet>
</databaseChangeLog>
